sathybrid/__init__.py
sathybrid/blur.py
sathybrid/denoise_model.py
sathybrid/kernels.py
sathybrid/main.py
sathybrid/resize.py
sathybrid/utils.py
sathybrid-0.2.0.dist-info/LICENSE
sathybrid-0.2.0.dist-info/METADATA
sathybrid-0.2.0.dist-info/WHEEL
sathybrid-0.2.0.dist-info/RECORD
