Metadata-Version: 2.1
Name: sathybrid
Version: 0.2.0
Summary: A Python package to fusion LR and HR imagery
Home-page: https://github.com/csaybar/sathybrid
Author: Cesar Aybar
Author-email: fcesar.aybar@uv.es
Requires-Python: >=3.9,<4.0
Classifier: Programming Language :: Python :: 3
Classifier: Programming Language :: Python :: 3.9
Classifier: Programming Language :: Python :: 3.10
Classifier: Programming Language :: Python :: 3.11
Classifier: Programming Language :: Python :: 3.12
Requires-Dist: numpy (>=1.26.4,<2.0.0)
Requires-Dist: pandas (>=2.1.4)
Requires-Dist: rasterio (>=1.3.10)
Requires-Dist: requests (>=2.32.3)
Requires-Dist: scikit-image (>=0.23.2)
Requires-Dist: timm (>=1.0.8)
Requires-Dist: torch (>=2.3.1)
Project-URL: Documentation, https://csaybar.github.io/sathybrid/
Project-URL: Repository, https://github.com/csaybar/sathybrid
